pyfec
